{
  "gitSyncId": "6758d65e1bd34772e5c66576_195860a8-37df-4b66-a3bb-383235431bab",
  "id": "Autor_SelectQuery",
  "pluginId": "mysql-plugin",
  "pluginType": "DB",
  "unpublishedAction": {
    "actionConfiguration": {
      "body": "SELECT * FROM autor\nWHERE nome_autor like '%{{data_table.searchText || \"\"}}%'\nORDER BY {{data_table.sortOrder.column || 'id'}} {{data_table.sortOrder.order || \"ASC\"}}\nLIMIT {{data_table.pageSize}}\nOFFSET {{(data_table.pageNo - 1) * data_table.pageSize}};",
      "encodeParamsToggle": true,
      "paginationType": "NONE",
      "pluginSpecifiedTemplates": [
        {
          "value": false
        }
      ],
      "timeoutInMillisecond": 10000
    },
    "confirmBeforeExecute": false,
    "datasource": {
      "id": "Untitled datasource 1",
      "isAutoGenerated": false,
      "name": "Untitled datasource 1",
      "pluginId": "mysql-plugin"
    },
    "executeOnLoad": true,
    "name": "SelectQuery",
    "pageId": "Autor",
    "userSetOnLoad": true
  }
}